FeaSc/__init__.py
FeaSc/pyFeaSc.py
FeaSc/pyPaaSc.py
FeaSc/pySaaSc.py
FeaSc/util_harmony.py
FeaSc/util_mca.py
FeaSc/util_stamp.py
examples/harmony_benchmark.py
feasc-1.1.5.dist-info/licenses/LICENSE
tests/__init__.py
tests/test_mca.py
tests/test_pyFeaSc.py
tests/test_pyPaaSc.py
tests/test_pySaaSc.py
tests/test_scamp.py
feasc-1.1.5.dist-info/METADATA
feasc-1.1.5.dist-info/WHEEL
feasc-1.1.5.dist-info/top_level.txt
feasc-1.1.5.dist-info/RECORD
